pygments_kakoune.py
pygments_kakoune-0.1.1.dist-info/METADATA
pygments_kakoune-0.1.1.dist-info/WHEEL
pygments_kakoune-0.1.1.dist-info/entry_points.txt
pygments_kakoune-0.1.1.dist-info/licenses/LICENSE
pygments_kakoune-0.1.1.dist-info/RECORD
