Metadata-Version: 2.4
Name: pygments-kakoune
Version: 0.1.1
Summary: Pygments lexer for Kakoune
Project-URL: Repository, https://codeberg.org/ficd/pygments-kakoune
Author-email: Daniel Fichtinger <daniel@ficd.ca>
License-File: LICENSE
Requires-Python: >=3.12
Requires-Dist: pygments>=2.19.2
